{
  "id": "vaporis_atrium",
  "name": "Atrium Magnum",
  "kind": "tilemap",
  "intent": "The Lyceum's great hall: marble floor (walkable stone via atlas mechanics override), central mosaic, column rows, braziers, the founder in bronze. Interior twin of vaporis_lyceum.",
  "tilemap": {
    "atlas": "vaporis_interior",
    "tile_size": 32,
    "grid_size": [
      28,
      18
    ],
    "layers": [
      {
        "name": "floor",
        "palette": {
          "s": "stone",
          "p": "path",
          "w": "water"
        },
        "rows": [
          "wwwwwwwwwwwwwwwwwwwwwwwwwwww",
          "wwwwwwwwwwwwwwwwwwwwwwwwwwww",
          "wssssssssssssssssssssssssssw",
          "wssssssssssssssssssssssssssw",
          "wssssssssssssssssssssssssssw",
          "wssssssssssssssssssssssssssw",
          "wssssssssssssssssssssssssssw",
          "wsssssssssppppppppsssssssssw",
          "wsssssssssppppppppsssssssssw",
          "wsssssssssppppppppsssssssssw",
          "wsssssssssppppppppsssssssssw",
          "wssssssssssssssssssssssssssw",
          "wssssssssssssssssssssssssssw",
          "wssssssssssssssssssssssssssw",
          "wssssssssssssssssssssssssssw",
          "wssssssssssssssssssssssssssw",
          "wssssssssssssppssssssssssssw",
          "wwwwwwwwwwwwwppwwwwwwwwwwwww"
        ]
      }
    ]
  },
  "props": [
    {
      "prop": "intact_0",
      "pos": [
        208,
        192
      ]
    },
    {
      "prop": "intact_1",
      "pos": [
        688,
        192
      ]
    },
    {
      "prop": "intact_1",
      "pos": [
        208,
        320
      ]
    },
    {
      "prop": "intact_0",
      "pos": [
        688,
        320
      ],
      "flip_h": true
    },
    {
      "prop": "intact_0",
      "pos": [
        208,
        448
      ]
    },
    {
      "prop": "intact_1",
      "pos": [
        688,
        448
      ]
    },
    {
      "prop": "standing_0",
      "pos": [
        208,
        256
      ]
    },
    {
      "prop": "standing_0",
      "pos": [
        688,
        256
      ]
    },
    {
      "prop": "standing_0",
      "pos": [
        208,
        384
      ]
    },
    {
      "prop": "standing_0",
      "pos": [
        688,
        384
      ]
    },
    {
      "prop": "founder_0",
      "pos": [
        432,
        160
      ]
    },
    {
      "prop": "marble_0",
      "pos": [
        368,
        224
      ]
    },
    {
      "prop": "marble_0",
      "pos": [
        528,
        224
      ],
      "flip_h": true
    },
    {
      "prop": "sphere_0",
      "pos": [
        112,
        512
      ]
    },
    {
      "prop": "sphere_0",
      "pos": [
        784,
        512
      ],
      "flip_h": true
    }
  ],
  "player": {
    "pos": [
      448,
      500
    ]
  },
  "spawns": [
    {
      "tag": "entrance",
      "pos": [
        448,
        500
      ]
    }
  ],
  "teleports": [
    {
      "target_level": "vaporis_lyceum",
      "target_spawn_tag": "atrium_steps",
      "rect": {
        "pos": [
          416,
          560
        ],
        "size": [
          64,
          16
        ]
      }
    }
  ],
  "npc_slots": [
    {
      "tag": "rector_indoors",
      "pos": [
        480,
        180
      ]
    },
    {
      "tag": "librarian",
      "pos": [
        220,
        300
      ]
    },
    {
      "tag": "student_e",
      "pos": [
        600,
        400
      ]
    },
    {
      "tag": "student_f",
      "pos": [
        320,
        430
      ]
    }
  ]
}
